modulos_pruebas/receptor/bram_tb/v1/bram_counter.v
module bram_counter (
    input           clk,
    input           hab,
    input           valid,
    input           rst,
    // SALIDA
    output          enable,
    output [31:0]   addr
);

//////////////////////////////////////////////////////////////////////////////////
//      CONSTANST
//////////////////////////////////////////////////////////////////////////////////
parameter COUNT_MAX = 2;
parameter POS_DIG   = 2;
//////////////////////////////////////////////////////////////////////////////////
//      WIRE AND REGISTERS
//////////////////////////////////////////////////////////////////////////////////

reg                 bandera = 0;
reg [7:0]           count = 0;
reg [31:0]          addr_count = 0;


always @(posedge clk) begin
    if(rst) begin
        addr_count <= 0;
    end else begin
        if(!hab && valid && !bandera) begin
            bandera <= 1'b1;
        end

        if(bandera) begin
            if (count < COUNT_MAX) begin
                count       <= count + 1;
            end else begin
                count       <= 1'b0;
                addr_count  <= addr_count + 1;
                bandera     <= 1'b0;
            end
        end
    end
end


//////////////////////////////////////////////////////////////////////////////////
//      SALIDAS
//////////////////////////////////////////////////////////////////////////////////

assign addr         = addr_count;
assign enable       = addr_count[POS_DIG];

endmodule

modulos_pruebas/receptor/bram_tb/v0/bram_counter_tb.v
`timescale 1ns / 1ps

module bram_counter_tb;

    parameter PERIOD_CLOK = 8.138;

    // Entradas
    reg             clk;
    reg             valid;
    reg             rst;
    // Salidas
    wire            en;
    wire [31:0]     addr;
    
    // Instancia del módulo bajo prueba
    bram_counter dut_counter (
        //LI
        .clk(clk),
        .hab(en),
        .valid(valid),
        .rst(rst),
        //LD
        .enable(en),
        .addr(addr)
    );

    // Generador de reloj
    always #4.069 clk = ~clk;

    // Inicialización de señales
    initial begin
        // Con esto puedo abrir el GTKWave
        $dumpfile("bram_counter_tb.vcd");
        $dumpvars(0,bram_counter_tb);

        clk     = 0;
        valid   = 0;
        rst     = 0;
        #(4.5*PERIOD_CLOK);
        
        // +1
        valid   = 1;
        #(PERIOD_CLOK);
        valid   = 0;
        #(10*PERIOD_CLOK);
        
        // +2
        valid   = 1;
        #(PERIOD_CLOK);
        valid   = 0;
        #(10*PERIOD_CLOK);
        
        // +3
        valid   = 1;
        #(PERIOD_CLOK);
        valid   = 0;
        #(10*PERIOD_CLOK);
        

        // +4
        valid   = 1;
        #(PERIOD_CLOK);
        valid   = 0;
        #(10*PERIOD_CLOK);
        
        // +5
        valid   = 1;
        #(PERIOD_CLOK);
        valid   = 0;
        #(10*PERIOD_CLOK);

        // +6
        valid   = 1;
        #(PERIOD_CLOK);
        valid   = 0;
        #(10*PERIOD_CLOK);

        // +7
        valid   = 1;
        #(PERIOD_CLOK);
        valid   = 0;
        #(10*PERIOD_CLOK);

        //RST
        rst     = 1;
        #(PERIOD_CLOK);
        rst     = 0;

        // +1
        #(PERIOD_CLOK);
        valid   = 1;
        #(PERIOD_CLOK);
        valid   = 0;
        #(10*PERIOD_CLOK);
        // +2
        valid   = 1;
        #(PERIOD_CLOK);
        valid   = 0;
        #(10*PERIOD_CLOK);



        #(50*PERIOD_CLOK);
        $finish;
    end

    //initial begin
    //    $monitor("Time = %0t, Senial = %d, Senial Modulada = %d", $time, senial, senial_mod);
    //end

endmodule

modulos_pruebas/receptor/bram_tb/v0/bram_counter_tb.vcd
$date
	Sat Apr 13 18:22:26 2024
$end
$version
	Icarus Verilog
$end
$timescale
	1ps
$end
$scope module bram_counter_tb $end
$var wire 32 ! addr [31:0] $end
$var wire 1 " en $end
$var reg 1 # clk $end
$var reg 1 $ rst $end
$var reg 1 % valid $end
$scope module dut_counter $end
$var wire 32 & addr [31:0] $end
$var wire 1 ' clk $end
$var wire 1 " enable $end
$var wire 1 " hab $end
$var wire 1 ( rst $end
$var wire 1 ) valid $end
$var reg 32 * addr_count [31:0] $end
$var reg 1 + bandera $end
$var reg 8 , count [7:0] $end
$upscope $end
$upscope $end
$enddefinitions $end
#0
$dumpvars
b0 ,
0+
b0 *
0)
0(
0'
b0 &
0%
0$
0#
0"
b0 !
$end
#4069
1#
1'
#8138
0#
0'
#12207
1#
1'
#16276
0#
0'
#20345
1#
1'
#24414
0#
0'
#28483
1#
1'
#32552
0#
0'
#36621
1+
1#
1'
1%
1)
#40690
0#
0'
#44759
b1 ,
1#
1'
0%
0)
#48828
0#
0'
#52897
b10 ,
1#
1'
#56966
0#
0'
#61035
0+
b1 *
b1 !
b1 &
b0 ,
1#
1'
#65104
0#
0'
#69173
1#
1'
#73242
0#
0'
#77311
1#
1'
#81380
0#
0'
#85449
1#
1'
#89518
0#
0'
#93587
1#
1'
#97656
0#
0'
#101725
1#
1'
#105794
0#
0'
#109863
1#
1'
#113932
0#
0'
#118001
1#
1'
#122070
0#
0'
#126139
1+
1#
1'
1%
1)
#130208
0#
0'
#134277
b1 ,
1#
1'
0%
0)
#138346
0#
0'
#142415
b10 ,
1#
1'
#146484
0#
0'
#150553
0+
b10 *
b10 !
b10 &
b0 ,
1#
1'
#154622
0#
0'
#158691
1#
1'
#162760
0#
0'
#166829
1#
1'
#170898
0#
0'
#174967
1#
1'
#179036
0#
0'
#183105
1#
1'
#187174
0#
0'
#191243
1#
1'
#195312
0#
0'
#199381
1#
1'
#203450
0#
0'
#207519
1#
1'
#211588
0#
0'
#215657
1+
1#
1'
1%
1)
#219726
0#
0'
#223795
b1 ,
1#
1'
0%
0)
#227864
0#
0'
#231933
b10 ,
1#
1'
#236002
0#
0'
#240071
0+
b11 *
b11 !
b11 &
b0 ,
1#
1'
#244140
0#
0'
#248209
1#
1'
#252278
0#
0'
#256347
1#
1'
#260416
0#
0'
#264485
1#
1'
#268554
0#
0'
#272623
1#
1'
#276692
0#
0'
#280761
1#
1'
#284830
0#
0'
#288899
1#
1'
#292968
0#
0'
#297037
1#
1'
#301106
0#
0'
#305175
1+
1#
1'
1%
1)
#309244
0#
0'
#313313
b1 ,
1#
1'
0%
0)
#317382
0#
0'
#321451
b10 ,
1#
1'
#325520
0#
0'
#329589
1"
0+
b100 *
b100 !
b100 &
b0 ,
1#
1'
#333658
0#
0'
#337727
1#
1'
#341796
0#
0'
#345865
1#
1'
#349934
0#
0'
#354003
1#
1'
#358072
0#
0'
#362141
1#
1'
#366210
0#
0'
#370279
1#
1'
#374348
0#
0'
#378417
1#
1'
#382486
0#
0'
#386555
1#
1'
#390624
0#
0'
#394693
1#
1'
1%
1)
#398762
0#
0'
#402831
1#
1'
0%
0)
#406900
0#
0'
#410969
1#
1'
#415038
0#
0'
#419107
1#
1'
#423176
0#
0'
#427245
1#
1'
#431314
0#
0'
#435383
1#
1'
#439452
0#
0'
#443521
1#
1'
#447590
0#
0'
#451659
1#
1'
#455728
0#
0'
#459797
1#
1'
#463866
0#
0'
#467935
1#
1'
#472004
0#
0'
#476073
1#
1'
#480142
0#
0'
#484211
1#
1'
1%
1)
#488280
0#
0'
#492349
1#
1'
0%
0)
#496418
0#
0'
#500487
1#
1'
#504556
0#
0'
#508625
1#
1'
#512694
0#
0'
#516763
1#
1'
#520832
0#
0'
#524901
1#
1'
#528970
0#
0'
#533039
1#
1'
#537108
0#
0'
#541177
1#
1'
#545246
0#
0'
#549315
1#
1'
#553384
0#
0'
#557453
1#
1'
#561522
0#
0'
#565591
1#
1'
#569660
0#
0'
#573729
1#
1'
1%
1)
#577798
0#
0'
#581867
1#
1'
0%
0)
#585936
0#
0'
#590005
1#
1'
#594074
0#
0'
#598143
1#
1'
#602212
0#
0'
#606281
1#
1'
#610350
0#
0'
#614419
1#
1'
#618488
0#
0'
#622557
1#
1'
#626626
0#
0'
#630695
1#
1'
#634764
0#
0'
#638833
1#
1'
#642902
0#
0'
#646971
1#
1'
#651040
0#
0'
#655109
1#
1'
#659178
0#
0'
#663247
0"
b0 *
b0 !
b0 &
1#
1'
1$
1(
#667316
0#
0'
#671385
1#
1'
0$
0(
#675454
0#
0'
#679523
1+
1#
1'
1%
1)
#683592
0#
0'
#687661
b1 ,
1#
1'
0%
0)
#691730
0#
0'
#695799
b10 ,
1#
1'
#699868
0#
0'
#703937
0+
b1 *
b1 !
b1 &
b0 ,
1#
1'
#708006
0#
0'
#712075
1#
1'
#716144
0#
0'
#720213
1#
1'
#724282
0#
0'
#728351
1#
1'
#732420
0#
0'
#736489
1#
1'
#740558
0#
0'
#744627
1#
1'
#748696
0#
0'
#752765
1#
1'
#756834
0#
0'
#760903
1#
1'
#764972
0#
0'
#769041
1+
1#
1'
1%
1)
#773110
0#
0'
#777179
b1 ,
1#
1'
0%
0)
#781248
0#
0'
#785317
b10 ,
1#
1'
#789386
0#
0'
#793455
0+
b10 *
b10 !
b10 &
b0 ,
1#
1'
