hardware/rx/bram_tb/v0/bram_ctrl.v
module bram_ctrl (
    input           clk,
    input           en,
    // RESET CONTADOR
    output          rst_count,
    // ESCRITURA PARA EL PS
    input  [31:0]   dout,
    output          valid,
    output [31:0]   din,
    output [31:0]   addr
);

//////////////////////////////////////////////////////////////////////////////////
//      CONSTANS
//////////////////////////////////////////////////////////////////////////////////
parameter ADDRS = 2047;

//////////////////////////////////////////////////////////////////////////////////
//      WIRE AND REGISTERS
//////////////////////////////////////////////////////////////////////////////////

//RESET DEL CONTADOR
reg                 rst_reg = 0;
//ESCRITURA EN BRAM
reg [31:0]          datos_reg = 0;
reg [31:0]          addr_reg = 0;
reg                 valid_reg = 0;
reg                 bandera = 0;
reg [7:0]           count = 0;


always @(posedge clk) begin
    if(en && !bandera && !rst_reg) begin
        datos_reg   <= 1'b1;
        valid_reg   <= 1'b1;
        bandera     <= 1'b1;
        count       <= 1'b0;
    end
    // Retardo para asegurar la escritura por parte del PL
    if (bandera && valid_reg) begin
        if (count < 2) begin
            count       <= count + 1;
        end else begin
            count       <= 1'b0;
            valid_reg   <= 1'b0;
        end
    end 

    if(bandera && !valid_reg && !dout[0]) begin
        rst_reg         <= 1'b1;
        bandera         <= 1'b0;
        datos_reg       <= 1'b0;
    end else begin
        rst_reg         <= 1'b0;
    end
end


//////////////////////////////////////////////////////////////////////////////////
//      SALIDAS
//////////////////////////////////////////////////////////////////////////////////

assign rst_count    = rst_reg;
assign valid        = valid_reg;
assign din          = datos_reg;
assign addr         = ADDRS;

endmodule

hardware/rx/bram_tb/v1/bram_ctrl_tb.v
`timescale 1ns / 1ps

module bram_ctrl_tb;

    parameter PERIOD_CLOK = 8.138;

    // Entradas
    reg             clk;
    reg             en;
    reg  [31:0]     dout;

    // Salidas
    wire            rst_count;
    wire            valid;
    wire [31:0]     din;
    wire [31:0]     addr;
    


    // Instancia del módulo bajo prueba
    bram_ctrl dut_bram (
        //LI
        .clk(clk),
        .en(en),
        .rst_count(rst_count),
        //LD
        .dout(dout),
        .din(din),
        .valid(valid),
        .addr(addr)
    );

    // Generador de reloj
    always #4.069 clk = ~clk;

    // Inicialización de señales
    initial begin
        // Con esto puedo abrir el GTKWave
        $dumpfile("bram_ctrl_tb.vcd");
        $dumpvars(0,bram_ctrl_tb);

        clk     = 0;
        en      = 0;
        dout    = 1;
        #(10.5*PERIOD_CLOK);
        en      = 1;
        #(10*PERIOD_CLOK);
        dout    = 0;
        #(2*PERIOD_CLOK);
        en      = 0;
        #(50*PERIOD_CLOK);
        $finish;
    end

    //initial begin
    //    $monitor("Time = %0t, Senial = %d, Senial Modulada = %d", $time, senial, senial_mod);
    //end

endmodule

modulos_pruebas/receptor/bram_tb/v0/bram_ctrl_tb.vcd
$date
	Sat Apr 13 17:42:07 2024
$end
$version
	Icarus Verilog
$end
$timescale
	1ps
$end
$scope module bram_ctrl_tb $end
$var wire 32 ! addr [31:0] $end
$var wire 32 " din [31:0] $end
$var wire 1 # rst_count $end
$var wire 1 $ valid $end
$var reg 1 % clk $end
$var reg 32 & dout [31:0] $end
$var reg 1 ' en $end
$scope module dut_bram $end
$var wire 32 ( addr [31:0] $end
$var wire 1 ) clk $end
$var wire 32 * din [31:0] $end
$var wire 32 + dout [31:0] $end
$var wire 1 , en $end
$var wire 1 # rst_count $end
$var wire 1 $ valid $end
$var reg 32 - addr_reg [31:0] $end
$var reg 1 . bandera $end
$var reg 8 / count [7:0] $end
$var reg 32 0 datos_reg [31:0] $end
$var reg 1 1 rst_reg $end
$var reg 1 2 valid_reg $end
$upscope $end
$upscope $end
$enddefinitions $end
#0
$dumpvars
02
01
b0 0
b0 /
0.
b0 -
0,
b1 +
b0 *
0)
b11111111111 (
0'
b1 &
0%
0$
0#
b0 "
b11111111111 !
$end
#4069
1%
1)
#8138
0%
0)
#12207
1%
1)
#16276
0%
0)
#20345
1%
1)
#24414
0%
0)
#28483
1%
1)
#32552
0%
0)
#36621
1%
1)
#40690
0%
0)
#44759
1%
1)
#48828
0%
0)
#52897
1%
1)
#56966
0%
0)
#61035
1%
1)
#65104
0%
0)
#69173
1%
1)
#73242
0%
0)
#77311
1%
1)
#81380
0%
0)
#85449
1.
12
1$
b1 0
b1 "
b1 *
1%
1)
1'
1,
#89518
0%
0)
#93587
b1 /
1%
1)
#97656
0%
0)
#101725
b10 /
1%
1)
#105794
0%
0)
#109863
02
0$
b0 /
1%
1)
#113932
0%
0)
#118001
1%
1)
#122070
0%
0)
#126139
1%
1)
#130208
0%
0)
#134277
1%
1)
#138346
0%
0)
#142415
1%
1)
#146484
0%
0)
#150553
1%
1)
#154622
0%
0)
#158691
1%
1)
#162760
0%
0)
#166829
b0 0
b0 "
b0 *
0.
11
1#
1%
1)
b0 &
b0 +
#170898
0%
0)
#174967
01
0#
1%
1)
#179036
0%
0)
#183105
1%
1)
0'
0,
