modulos_pruebas/receptor/bram_tb/v0/bram_mult.v
module bram_mult (
    input               clk,
    input               en,
    //ENT1
    input   [31:0]      addr1,
    input   [31:0]      din1,
    output  [31:0]      dout1,
    input               valid1,
    //ENT2
    input   [31:0]      addr2,
    input   [31:0]      din2,
    output  [31:0]      dout2,
    input               valid2,
    // SALIDA
    output              valid,
    output              enable,
    output  [31:0]      addr,
    output  [31:0]      din,
    input   [31:0]      dout
);

//////////////////////////////////////////////////////////////////////////////////
//      SALIDAS
//////////////////////////////////////////////////////////////////////////////////

assign enable       = 1'b1;
assign addr         = (!en) ? addr1  : addr2;
assign din          = (!en) ? din1   : din2;
assign valid        = (!en) ? valid1 : valid2;
assign dout1        = (!en) ? dout   : 32'b1;
assign dout2        =  (en) ? dout   : 32'b1;

endmodule

hardware/rx/bram_tb/v0/bram_ctrl.v
module bram_ctrl (
    input           clk,
    input           en,
    // RESET CONTADOR
    output          rst_count,
    // ESCRITURA PARA EL PS
    input  [31:0]   dout,
    output          valid,
    output [31:0]   din,
    output [31:0]   addr
);

//////////////////////////////////////////////////////////////////////////////////
//      CONSTANS
//////////////////////////////////////////////////////////////////////////////////
parameter ADDRS = 2047;

//////////////////////////////////////////////////////////////////////////////////
//      WIRE AND REGISTERS
//////////////////////////////////////////////////////////////////////////////////

//RESET DEL CONTADOR
reg                 rst_reg = 0;
//ESCRITURA EN BRAM
reg [31:0]          datos_reg = 0;
reg [31:0]          addr_reg = 0;
reg                 valid_reg = 0;
reg                 bandera = 0;
reg [7:0]           count = 0;


always @(posedge clk) begin
    if(en && !bandera && !rst_reg) begin
        datos_reg   <= 1'b1;
        valid_reg   <= 1'b1;
        bandera     <= 1'b1;
        count       <= 1'b0;
    end
    // Retardo para asegurar la escritura por parte del PL
    if (bandera && valid_reg) begin
        if (count < 2) begin
            count       <= count + 1;
        end else begin
            count       <= 1'b0;
            valid_reg   <= 1'b0;
        end
    end 

    if(bandera && !valid_reg && !dout[0]) begin
        rst_reg         <= 1'b1;
        bandera         <= 1'b0;
        datos_reg       <= 1'b0;
    end else begin
        rst_reg         <= 1'b0;
    end
end


//////////////////////////////////////////////////////////////////////////////////
//      SALIDAS
//////////////////////////////////////////////////////////////////////////////////

assign rst_count    = rst_reg;
assign valid        = valid_reg;
assign din          = datos_reg;
assign addr         = ADDRS;

endmodule

modulos_pruebas/receptor/bram_tb/v1/bram_counter.v
module bram_counter (
    input           clk,
    input           hab,
    input           valid,
    input           rst,
    // SALIDA
    output          enable,
    output [31:0]   addr
);

//////////////////////////////////////////////////////////////////////////////////
//      CONSTANST
//////////////////////////////////////////////////////////////////////////////////
parameter COUNT_MAX = 2;
parameter POS_DIG   = 2;
//////////////////////////////////////////////////////////////////////////////////
//      WIRE AND REGISTERS
//////////////////////////////////////////////////////////////////////////////////

reg                 bandera = 0;
reg [7:0]           count = 0;
reg [31:0]          addr_count = 0;


always @(posedge clk) begin
    if(rst) begin
        addr_count <= 0;
    end else begin
        if(!hab && valid && !bandera) begin
            bandera <= 1'b1;
        end

        if(bandera) begin
            if (count < COUNT_MAX) begin
                count       <= count + 1;
            end else begin
                count       <= 1'b0;
                addr_count  <= addr_count + 1;
                bandera     <= 1'b0;
            end
        end
    end
end


//////////////////////////////////////////////////////////////////////////////////
//      SALIDAS
//////////////////////////////////////////////////////////////////////////////////

assign addr         = addr_count;
assign enable       = addr_count[POS_DIG];

endmodule

modulos_pruebas/receptor/bram_tb/v0/bram_int.v
module bram_int (
    // Entradas
    input               clk,
    input               valid,
    input   [31:0]      datos,
    // Salidas
    output              enable,
    output              we,
    input   [31:0]      dout,
    output  [31:0]      addr,
    output  [31:0]      din
);

//////////////////////////////////////////////////////////////////////////////////
//      WIRE AND REGISTERS
//////////////////////////////////////////////////////////////////////////////////

wire [31:0]         dout1;
//CONTADOR
wire                en;
wire                rst_ctrl;
wire [31:0]         addr_count;

//CTRL
wire                valid_ctrl;
wire [31:0]         dout_ctrl;
wire [31:0]         addr_ctrl;
wire [31:0]         din_ctrl;


//COMPUERTA AND
wire                valid_and;

//SALIDA
wire                enable_wire;
wire                we_wire;
wire [31:0]         dout_wire;
wire [31:0]         addr_wire;
wire [31:0]         din_wire;
//////////////////////////////////////////////////////////////////////////////////
//      LOGICA
//////////////////////////////////////////////////////////////////////////////////

bram_counter counter_inst (
    //LI
    .clk(clk),
    .hab(en),
    .valid(valid),
    .rst(rst_ctrl),
    //LD
    .enable(en),
    .addr(addr_count)
);

bram_ctrl ctrl_inst (
    //LI
    .clk(clk),
    .en(en),
    .rst_count(rst_ctrl),
    //LD
    .dout(dout_ctrl),
    .din(din_ctrl),
    .valid(valid_ctrl),
    .addr(addr_ctrl)
);


assign valid_and = (!en) && valid;

bram_mult multiplexor_inst(
    .clk(clk),
    .en(en),
    //ENT1
    .addr1(addr_count),
    .din1(datos),
    .dout1(dout1),
    .valid1(valid_and),
    //ENT2
    .addr2(addr_ctrl),
    .din2(din_ctrl),
    .dout2(dout_ctrl),
    .valid2(valid_ctrl),
    //SALIDA
    .valid(we),
    .enable(enable),
    .addr(addr),
    .din(din),
    .dout(dout)
);

//////////////////////////////////////////////////////////////////////////////////
//      SALIDAS
//////////////////////////////////////////////////////////////////////////////////

//assign enable   = enable_wire;
//assign valid    = we_wire;
//assign addr     = addr_wire;
//assign din      = din_wire;

endmodule

hardware/rx/bram_tb/v0/bram_int_tb.v
`timescale 1ns / 1ps

module bram_int_tb;

    parameter PERIOD_CLOK = 8.138;

    // Entradas
    reg             clk = 0;
    reg             valid = 0;
    reg  [31:0]     datos = 32'b1111;
    reg  [31:0]     dout = 1'b1;

    // Salidas
    wire            enable;
    wire            we;
    wire [31:0]     din;
    wire [31:0]     addr;


    // Instancia del módulo bajo prueba
    bram_int dut_int(
        //LI
        .clk(clk),
        .valid(valid),
        .datos(datos),
        //LD
        .enable(enable),
        .dout(dout),
        .din(din),
        .we(we),
        .addr(addr)
    );

    // Generador de reloj
    always #4.069 clk = ~clk;

    // Inicialización de señales
    initial begin
        // Con esto puedo abrir el GTKWave
        $dumpfile("bram_int_tb.vcd");
        $dumpvars(0,bram_int_tb);

        clk     = 0;
        valid   = 0;
        datos   = 0;
        dout    = 0;
        #(4.5*PERIOD_CLOK);
        
        // +1
        valid   = 1;
        #(PERIOD_CLOK);
        valid   = 0;
        #(10*PERIOD_CLOK);
        
        // +2
        valid   = 1;
        #(PERIOD_CLOK);
        valid   = 0;
        #(10*PERIOD_CLOK);
        
        // +3
        valid   = 1;
        #(PERIOD_CLOK);
        valid   = 0;
        #(10*PERIOD_CLOK);
        

        // +4
        valid   = 1;
        #(PERIOD_CLOK);
        dout    = 1;
        valid   = 0;
        #(10*PERIOD_CLOK);
        
        // +5
        valid   = 1;
        #(PERIOD_CLOK);
        valid   = 0;
        #(10*PERIOD_CLOK);

        // +6
        valid   = 1;
        #(PERIOD_CLOK);
        valid   = 0;
        #(10*PERIOD_CLOK);

        // +7
        valid   = 1;
        #(PERIOD_CLOK);
        valid   = 0;
        #(10*PERIOD_CLOK);

        //REINICIO MEDIANTE DOUT
        dout = 1'b0;
        #(PERIOD_CLOK);

        // +1
        #(PERIOD_CLOK);
        valid   = 1;
        #(PERIOD_CLOK);
        valid   = 0;
        #(10*PERIOD_CLOK);
        // +2
        valid   = 1;
        #(PERIOD_CLOK);
        valid   = 0;
        #(10*PERIOD_CLOK);



        #(50*PERIOD_CLOK);
        $finish;
    end

    //initial begin
    //    $monitor("Time = %0t, Senial = %d, Senial Modulada = %d", $time, senial, senial_mod);
    //end

endmodule

modulos_pruebas/receptor/bram_tb/v0/bram_int_tb.vcd
$date
	Thu Apr 18 17:02:30 2024
$end
$version
	Icarus Verilog
$end
$timescale
	1ps
$end
$scope module bram_int_tb $end
$var wire 32 ! addr [31:0] $end
$var wire 32 " din [31:0] $end
$var wire 1 # enable $end
$var wire 1 $ we $end
$var reg 1 % clk $end
$var reg 32 & datos [31:0] $end
$var reg 32 ' dout [31:0] $end
$var reg 1 ( valid $end
$scope module dut_int $end
$var wire 32 ) addr [31:0] $end
$var wire 32 * addr_count [31:0] $end
$var wire 32 + addr_ctrl [31:0] $end
$var wire 1 , clk $end
$var wire 32 - datos [31:0] $end
$var wire 32 . din [31:0] $end
$var wire 32 / din_ctrl [31:0] $end
$var wire 32 0 dout [31:0] $end
$var wire 32 1 dout1 [31:0] $end
$var wire 32 2 dout_ctrl [31:0] $end
$var wire 1 3 en $end
$var wire 1 # enable $end
$var wire 1 4 rst_ctrl $end
$var wire 1 5 valid $end
$var wire 1 6 valid_and $end
$var wire 1 7 valid_ctrl $end
$var wire 1 $ we $end
$scope module counter_inst $end
$var wire 32 8 addr [31:0] $end
$var wire 1 , clk $end
$var wire 1 3 enable $end
$var wire 1 3 hab $end
$var wire 1 4 rst $end
$var wire 1 5 valid $end
$var reg 32 9 addr_count [31:0] $end
$var reg 1 : bandera $end
$var reg 8 ; count [7:0] $end
$upscope $end
$scope module ctrl_inst $end
$var wire 32 < addr [31:0] $end
$var wire 1 , clk $end
$var wire 32 = din [31:0] $end
$var wire 32 > dout [31:0] $end
$var wire 1 3 en $end
$var wire 1 4 rst_count $end
$var wire 1 7 valid $end
$var reg 32 ? addr_reg [31:0] $end
$var reg 1 @ bandera $end
$var reg 8 A count [7:0] $end
$var reg 32 B datos_reg [31:0] $end
$var reg 1 C rst_reg $end
$var reg 1 D valid_reg $end
$upscope $end
$scope module multiplexor_inst $end
$var wire 32 E addr [31:0] $end
$var wire 32 F addr1 [31:0] $end
$var wire 32 G addr2 [31:0] $end
$var wire 1 , clk $end
$var wire 32 H din [31:0] $end
$var wire 32 I din1 [31:0] $end
$var wire 32 J din2 [31:0] $end
$var wire 32 K dout [31:0] $end
$var wire 32 L dout1 [31:0] $end
$var wire 32 M dout2 [31:0] $end
$var wire 1 3 en $end
$var wire 1 # enable $end
$var wire 1 $ valid $end
$var wire 1 6 valid1 $end
$var wire 1 7 valid2 $end
$upscope $end
$upscope $end
$upscope $end
$enddefinitions $end
#0
$dumpvars
b1 M
b0 L
b0 K
b0 J
b0 I
b0 H
b11111111111 G
b0 F
b0 E
0D
0C
b0 B
b0 A
0@
b0 ?
b1 >
b0 =
b11111111111 <
b0 ;
0:
b0 9
b0 8
07
06
05
04
03
b1 2
b0 1
b0 0
b0 /
b0 .
b0 -
0,
b11111111111 +
b0 *
b0 )
0(
b0 '
b0 &
0%
0$
1#
b0 "
b0 !
$end
#4069
1%
1,
#8138
0%
0,
#12207
1%
1,
#16276
0%
0,
#20345
1%
1,
#24414
0%
0,
#28483
1%
1,
#32552
0%
0,
#36621
1:
1$
16
1%
1,
1(
15
#40690
0%
0,
#44759
b1 ;
0$
06
1%
1,
0(
05
#48828
0%
0,
#52897
b10 ;
1%
1,
#56966
0%
0,
#61035
b1 !
b1 )
b1 E
0:
b1 9
b1 *
b1 8
b1 F
b0 ;
1%
1,
#65104
0%
0,
#69173
1%
1,
#73242
0%
0,
#77311
1%
1,
#81380
0%
0,
#85449
1%
1,
#89518
0%
0,
#93587
1%
1,
#97656
0%
0,
#101725
1%
1,
#105794
0%
0,
#109863
1%
1,
#113932
0%
0,
#118001
1%
1,
#122070
0%
0,
#126139
1:
1$
16
1%
1,
1(
15
#130208
0%
0,
#134277
b1 ;
0$
06
1%
1,
0(
05
#138346
0%
0,
#142415
b10 ;
1%
1,
#146484
0%
0,
#150553
b10 !
b10 )
b10 E
0:
b10 9
b10 *
b10 8
b10 F
b0 ;
1%
1,
#154622
0%
0,
#158691
1%
1,
#162760
0%
0,
#166829
1%
1,
#170898
0%
0,
#174967
1%
1,
#179036
0%
0,
#183105
1%
1,
#187174
0%
0,
#191243
1%
1,
#195312
0%
0,
#199381
1%
1,
#203450
0%
0,
#207519
1%
1,
#211588
0%
0,
#215657
1:
1$
16
1%
1,
1(
15
#219726
0%
0,
#223795
b1 ;
0$
06
1%
1,
0(
05
#227864
0%
0,
#231933
b10 ;
1%
1,
#236002
0%
0,
#240071
b11 !
b11 )
b11 E
0:
b11 9
b11 *
b11 8
b11 F
b0 ;
1%
1,
#244140
0%
0,
#248209
1%
1,
#252278
0%
0,
#256347
1%
1,
#260416
0%
0,
#264485
1%
1,
#268554
0%
0,
#272623
1%
1,
#276692
0%
0,
#280761
1%
1,
#284830
0%
0,
#288899
1%
1,
#292968
0%
0,
#297037
1%
1,
#301106
0%
0,
#305175
1:
1$
16
1%
1,
1(
15
#309244
0%
0,
#313313
b1 ;
0$
06
b1 1
b1 L
1%
1,
0(
05
b1 '
b1 0
b1 K
#317382
0%
0,
#321451
b10 ;
1%
1,
#325520
0%
0,
#329589
13
b11111111111 !
b11111111111 )
b11111111111 E
0:
b100 9
b100 *
b100 8
b100 F
b0 ;
1%
1,
#333658
0%
0,
#337727
1$
b1 "
b1 .
b1 H
1@
1D
17
b1 B
b1 /
b1 =
b1 J
1%
1,
#341796
0%
0,
#345865
b1 A
1%
1,
#349934
0%
0,
#354003
b10 A
1%
1,
#358072
0%
0,
#362141
0$
0D
07
b0 A
1%
1,
#366210
0%
0,
#370279
1%
1,
#374348
0%
0,
#378417
1%
1,
#382486
0%
0,
#386555
1%
1,
#390624
0%
0,
#394693
1%
1,
1(
15
#398762
0%
0,
#402831
1%
1,
0(
05
#406900
0%
0,
#410969
1%
1,
#415038
0%
0,
#419107
1%
1,
#423176
0%
0,
#427245
1%
1,
#431314
0%
0,
#435383
1%
1,
#439452
0%
0,
#443521
1%
1,
#447590
0%
0,
#451659
1%
1,
#455728
0%
0,
#459797
1%
1,
#463866
0%
0,
#467935
1%
1,
#472004
0%
0,
#476073
1%
1,
#480142
0%
0,
#484211
1%
1,
1(
15
#488280
0%
0,
#492349
1%
1,
0(
05
#496418
0%
0,
#500487
1%
1,
#504556
0%
0,
#508625
1%
1,
#512694
0%
0,
#516763
1%
1,
#520832
0%
0,
#524901
1%
1,
#528970
0%
0,
#533039
1%
1,
#537108
0%
0,
#541177
1%
1,
#545246
0%
0,
#549315
1%
1,
#553384
0%
0,
#557453
1%
1,
#561522
0%
0,
#565591
1%
1,
#569660
0%
0,
#573729
1%
1,
1(
15
#577798
0%
0,
#581867
1%
1,
0(
05
#585936
0%
0,
#590005
1%
1,
#594074
0%
0,
#598143
1%
1,
#602212
0%
0,
#606281
1%
1,
#610350
0%
0,
#614419
1%
1,
#618488
0%
0,
#622557
1%
1,
#626626
0%
0,
#630695
1%
1,
#634764
0%
0,
#638833
1%
1,
#642902
0%
0,
#646971
1%
1,
#651040
0%
0,
#655109
1%
1,
#659178
0%
0,
#663247
b0 "
b0 .
b0 H
b0 B
b0 /
b0 =
b0 J
0@
1C
14
b0 2
b0 >
b0 M
1%
1,
b0 '
b0 0
b0 K
#667316
0%
0,
#671385
b0 !
b0 )
b0 E
b0 1
b0 L
b1 2
b1 >
b1 M
03
b0 9
b0 *
b0 8
b0 F
0C
04
1%
1,
#675454
0%
0,
#679523
1:
1$
16
1%
1,
1(
15
#683592
0%
0,
#687661
b1 ;
0$
06
1%
1,
0(
05
#691730
0%
0,
#695799
b10 ;
1%
1,
#699868
0%
0,
#703937
b1 !
b1 )
b1 E
0:
b1 9
b1 *
b1 8
b1 F
b0 ;
1%
1,
#708006
0%
0,
#712075
1%
1,
#716144
0%
0,
#720213
1%
1,
#724282
0%
0,
#728351
1%
1,
#732420
0%
0,
#736489
1%
1,
#740558
0%
0,
#744627
1%
1,
#748696
0%
0,
#752765
1%
1,
#756834
0%
0,
#760903
1%
1,
#764972
0%
0,
#769041
1:
1$
16
1%
1,
1(
15
#773110
0%
0,
#777179
b1 ;
0$
06
1%
1,
0(
05
#781248
0%
0,
#785317
b10 ;
1%
1,
#789386
0%
0,
#793455
b10 !
b10 )
b10 E
0:
b10 9
b10 *
b10 8
b10 F
b0 ;
1%
1,
